odoo/addons/stock_quant_package_dimension_total_weight_from_packaging/__init__.py
odoo/addons/stock_quant_package_dimension_total_weight_from_packaging/__manifest__.py
odoo/addons/stock_quant_package_dimension_total_weight_from_packaging/i18n/stock_quant_package_dimension_total_weight_from_packaging.pot
odoo/addons/stock_quant_package_dimension_total_weight_from_packaging/models/__init__.py
odoo/addons/stock_quant_package_dimension_total_weight_from_packaging/models/stock_quant_package.py
odoo/addons/stock_quant_package_dimension_total_weight_from_packaging/static/description/icon.png
odoo/addons/stock_quant_package_dimension_total_weight_from_packaging/tests/__init__.py
odoo/addons/stock_quant_package_dimension_total_weight_from_packaging/tests/test_package_weight.py
odoo13_addon_stock_quant_package_dimension_total_weight_from_packaging-13.0.1.1.0.dist-info/METADATA
odoo13_addon_stock_quant_package_dimension_total_weight_from_packaging-13.0.1.1.0.dist-info/WHEEL
odoo13_addon_stock_quant_package_dimension_total_weight_from_packaging-13.0.1.1.0.dist-info/top_level.txt
odoo13_addon_stock_quant_package_dimension_total_weight_from_packaging-13.0.1.1.0.dist-info/RECORD
